utils/__init__.py
utils/utils.py
CommonCode_LeiLin-0.0.1.dist-info/LICENSE
CommonCode_LeiLin-0.0.1.dist-info/METADATA
CommonCode_LeiLin-0.0.1.dist-info/WHEEL
CommonCode_LeiLin-0.0.1.dist-info/top_level.txt
CommonCode_LeiLin-0.0.1.dist-info/RECORD
