Metadata-Version: 2.1
Name: CommonCode-LeiLin
Version: 0.0.1
Summary: This is the code base that Lei Lin commonly uses in his research.
Home-page: https://github.com/leilin1995/CommonCode
Author: leilin
Author-email: 919711601@qq.com
License: UNKNOWN
Platform: UNKNOWN
Classifier: Programming Language :: Python :: 3
Classifier: License :: OSI Approved :: MIT License
Classifier: Operating System :: OS Independent
License-File: LICENSE
